flask_apikit/__init__.py
flask_apikit/decorators.py
flask_apikit/exceptions.py
flask_apikit/responses.py
flask_apikit/views.py
flask_apikit/utils/__init__.py
flask_apikit/utils/query.py
Flask_APIKit-0.0.7.dist-info/LICENSE.md
Flask_APIKit-0.0.7.dist-info/METADATA
Flask_APIKit-0.0.7.dist-info/WHEEL
Flask_APIKit-0.0.7.dist-info/top_level.txt
Flask_APIKit-0.0.7.dist-info/RECORD
