Metadata-Version: 2.1
Name: Flask-APIKit
Version: 0.0.7
Summary: Build Restful API with Flask Quickly.
Home-page: https://github.com/kozzzx/flask-apikit
Author: kozzzx
Author-email: kozzzx@qq.com
License: BSD
Platform: any
Classifier: Environment :: Web Environment
Classifier: Intended Audience :: Developers
Classifier: License :: OSI Approved :: BSD License
Classifier: Operating System :: OS Independent
Classifier: Programming Language :: Python
Classifier: Topic :: Internet :: WWW/HTTP :: Dynamic Content
Classifier: Topic :: Software Development :: Libraries :: Python Modules
License-File: LICENSE.md
Requires-Dist: Flask >=1.0
Requires-Dist: marshmallow ==3.0.0b20
